mindoptpy/__init__.py
mindoptpy/__init__.pyi
mindoptpy/libmindopt.2.2.0.dylib
mindoptpy/mindoptpy.so
mindoptpy/osx64-x86/lib/libmindoptmilp.2.2.0.dylib
mindoptpy/osx64-x86/lib/libmindoptmiqcp.2.2.0.dylib
mindoptpy/osx64-x86/lib/libmindoptpower.2.2.0.dylib
mindoptpy-2.2.0.dist-info/METADATA
mindoptpy-2.2.0.dist-info/WHEEL
mindoptpy-2.2.0.dist-info/top_level.txt
mindoptpy-2.2.0.dist-info/RECORD
